nonebot_plugin_figure-0.1.0.dist-info/METADATA
nonebot_plugin_figure-0.1.0.dist-info/WHEEL
nonebot_plugin_figure/__init__.py
nonebot_plugin_figure-0.1.0.dist-info/RECORD
