Metadata-Version: 2.1
Name: nonebot-plugin-figure
Version: 0.1.0
Summary: 带有猜数字功能的猜数字
Author-Email: =?utf-8?b?5LiH5L+K6L6J?= <2401128923@qq.com>
License: apl3.0
Requires-Python: >=3.8
